{"playerInfo": {"nickname": "枫绫", "level": 57, "signature": "等待恋与提瓦特到来，邪王真眼，放逐这个世界", "worldLevel": 8, "nameCardId": 210081, "finishAchievementNum": 534, "towerFloorIndex": 12, "towerLevelIndex": 3, "showAvatarInfoList": [{"avatarId": 10000046, "level": 90}, {"avatarId": 10000052, "level": 90}, {"avatarId": 10000054, "level": 90}, {"avatarId": 10000037, "level": 90}, {"avatarId": 10000031, "level": 59, "costumeId": 203101}, {"avatarId": 10000002, "level": 88}, {"avatarId": 10000030, "level": 90}, {"avatarId": 10000066, "level": 89}], "showNameCardIdList": [210059, 210097, 210044, 210053, 210114, 210081, 210093, 210092, 210046], "profilePicture": {"avatarId": 10000031, "costumeId": 203101}}, "avatarInfoList": [{"avatarId": 10000046, "propMap": {"1001": {"type": 1001, "ival": "0"}, "1002": {"type": 1002, "ival": "6", "val": "6"}, "1003": {"type": 1003, "ival": "0"}, "1004": {"type": 1004, "ival": "0"}, "4001": {"type": 4001, "ival": "90", "val": "90"}, "10010": {"type": 10010, "ival": "24000", "val": "24000"}}, "fightPropMap": {"1": 15552.306640625, "2": 5019, "3": 0.8234000205993652, "4": 714.509033203125, "5": 363.52001953125, "7": 876.1519775390625, "8": 20.829999923706055, "20": 0.42329999804496765, "21": 0, "22": 3.0067360401153564, "23": 1.051800012588501, "26": 0, "27": 0, "28": 223.7899932861328, "29": 0, "30": 0, "40": 0.6159999966621399, "41": 0, "42": 0, "43": 0, "44": 0, "45": 0, "46": 0, "50": 0, "51": 0, "52": 0, "53": 0, "54": 0, "55": 0, "56": 0, "70": 60, "1000": 60, "1010": 20021.998046875, "2000": 33377.078125, "2001": 1345.045654296875, "2002": 896.9819946289062, "2003": 0, "3007": 0, "3015": 0, "3016": 0, "3017": 0, "3018": 0, "3019": 0, "3020": 0, "3021": 0}, "skillDepotId": 4601, "inherentProudSkillList": [462101, 462201, 462301], "skillLevelMap": {"10461": 10, "10462": 10, "10463": 10}, "equipList": [{"itemId": 80543, "reliquary": {"level": 21, "mainPropId": 14001, "appendPropIdList": [501204, 501224, 501243, 501054, 501222, 501202, 501202, 501221]}, "flat": {"nameTextMapHash": "1149648428", "setNameTextMapHash": "1524173875", "rankLevel": 5, "reliquaryMainstat": {"mainPropId": "FIGHT_PROP_HP", "statValue": 4780}, "reliquarySubstats": [{"appendPropId": "FIGHT_PROP_CRITICAL", "statValue": 10.1}, {"appendPropId": "FIGHT_PROP_CRITICAL_HURT", "statValue": 19.4}, {"appendPropId": "FIGHT_PROP_ELEMENT_MASTERY", "statValue": 21}, {"appendPropId": "FIGHT_PROP_ATTACK", "statValue": 19}], "itemType": "ITEM_RELIQUARY", "icon": "UI_RelicIcon_15006_4", "equipType": "EQUIP_BRACER"}}, {"itemId": 80523, "reliquary": {"level": 21, "mainPropId": 12001, "appendPropIdList": [501022, 501224, 501203, 501032, 501203, 501224, 501202, 501201]}, "flat": {"nameTextMapHash": "3216935684", "setNameTextMapHash": "1524173875", "rankLevel": 5, "reliquaryMainstat": {"mainPropId": "FIGHT_PROP_ATTACK", "statValue": 311}, "reliquarySubstats": [{"appendPropId": "FIGHT_PROP_HP", "statValue": 239}, {"appendPropId": "FIGHT_PROP_CRITICAL_HURT", "statValue": 15.5}, {"appendPropId": "FIGHT_PROP_CRITICAL", "statValue": 12.8}, {"appendPropId": "FIGHT_PROP_HP_PERCENT", "statValue": 4.7}], "itemType": "ITEM_RELIQUARY", "icon": "UI_RelicIcon_15006_2", "equipType": "EQUIP_NECKLACE"}}, {"itemId": 80554, "reliquary": {"level": 21, "mainPropId": 10002, "appendPropIdList": [501204, 501243, 501224, 501083, 501244, 501243, 501224, 501221, 501224]}, "flat": {"nameTextMapHash": "2155936948", "setNameTextMapHash": "1524173875", "rankLevel": 5, "reliquaryMainstat": {"mainPropId": "FIGHT_PROP_HP_PERCENT", "statValue": 46.6}, "reliquarySubstats": [{"appendPropId": "FIGHT_PROP_CRITICAL", "statValue": 3.9}, {"appendPropId": "FIGHT_PROP_ELEMENT_MASTERY", "statValue": 65}, {"appendPropId": "FIGHT_PROP_CRITICAL_HURT", "statValue": 28.8}, {"appendPropId": "FIGHT_PROP_DEFENSE", "statValue": 21}], "itemType": "ITEM_RELIQUARY", "icon": "UI_RelicIcon_15006_5", "equipType": "EQUIP_SHOES"}}, {"itemId": 74514, "reliquary": {"level": 21, "mainPropId": 15008, "appendPropIdList": [501232, 501221, 501241, 501034, 501224, 501244, 501241, 501223, 501244]}, "flat": {"nameTextMapHash": "813294060", "setNameTextMapHash": "83115355", "rankLevel": 5, "reliquaryMainstat": {"mainPropId": "FIGHT_PROP_FIRE_ADD_HURT", "statValue": 46.6}, "reliquarySubstats": [{"appendPropId": "FIGHT_PROP_CHARGE_EFFICIENCY", "statValue": 5.2}, {"appendPropId": "FIGHT_PROP_CRITICAL_HURT", "statValue": 20.2}, {"appendPropId": "FIGHT_PROP_ELEMENT_MASTERY", "statValue": 79}, {"appendPropId": "FIGHT_PROP_HP_PERCENT", "statValue": 5.8}], "itemType": "ITEM_RELIQUARY", "icon": "UI_RelicIcon_14004_1", "equipType": "EQUIP_RING"}}, {"itemId": 80534, "reliquary": {"level": 21, "mainPropId": 13008, "appendPropIdList": [501241, 501033, 501053, 501203, 501204, 501202, 501242, 501244, 501052]}, "flat": {"nameTextMapHash": "819231388", "setNameTextMapHash": "1524173875", "rankLevel": 5, "reliquaryMainstat": {"mainPropId": "FIGHT_PROP_CRITICAL_HURT", "statValue": 62.2}, "reliquarySubstats": [{"appendPropId": "FIGHT_PROP_ELEMENT_MASTERY", "statValue": 58}, {"appendPropId": "FIGHT_PROP_HP_PERCENT", "statValue": 5.3}, {"appendPropId": "FIGHT_PROP_ATTACK", "statValue": 33}, {"appendPropId": "FIGHT_PROP_CRITICAL", "statValue": 10.5}], "itemType": "ITEM_RELIQUARY", "icon": "UI_RelicIcon_15006_3", "equipType": "EQUIP_DRESS"}}, {"itemId": 13501, "weapon": {"level": 90, "promoteLevel": 6, "affixMap": {"113501": 0}}, "flat": {"nameTextMapHash": "3235324891", "rankLevel": 5, "weaponStats": [{"appendPropId": "FIGHT_PROP_BASE_ATTACK", "statValue": 608}, {"appendPropId": "FIGHT_PROP_CRITICAL_HURT", "statValue": 66.2}], "itemType": "ITEM_WEAPON", "icon": "UI_EquipIcon_Pole_Homa"}}], "fetterInfo": {"expLevel": 10}}, {"avatarId": 10000052, "propMap": {"1001": {"type": 1001, "ival": "0"}, "1002": {"type": 1002, "ival": "6", "val": "6"}, "1003": {"type": 1003, "ival": "0"}, "1004": {"type": 1004, "ival": "0"}, "4001": {"type": 4001, "ival": "90", "val": "90"}, "10010": {"type": 10010, "ival": "24000", "val": "24000"}}, "fightPropMap": {"1": 12907.1904296875, "2": 5287.8798828125, "3": 0.040800001472234726, "4": 791.6046752929688, "5": 392.6999816894531, "6": 0.6583999991416931, "7": 789.305419921875, "8": 37.040000915527344, "20": 0.7286199927330017, "21": 0, "22": 1.7125999927520752, "23": 2.5497000217437744, "26": 0, "27": 0, "28": 0, "29": 0, "30": 0, "40": 0, "41": 0.6198800206184387, "42": 0, "43": 0, "44": 0, "45": 0, "46": 0, "50": 0, "51": 0, "52": 0, "53": 0, "54": 0, "55": 0, "56": 0, "71": 90, "1001": 90, "1010": 18721.68359375, "2000": 18721.68359375, "2001": 1705.4971923828125, "2002": 826.3453979492188, "2003": 0}, "skillDepotId": 5201, "inherentProudSkillList": [522101, 522201, 522301, 522501], "skillLevelMap": {"10521": 6, "10522": 10, "10525": 10}, "equipList": [{"itemId": 94543, "reliquary": {"level": 21, "mainPropId": 14001, "appendPropIdList": [501232, 501221, 501061, 501051, 501233, 501233, 501233, 501231]}, "flat": {"nameTextMapHash": "2246743908", "setNameTextMapHash": "2276480763", "rankLevel": 5, "reliquaryMainstat": {"mainPropId": "FIGHT_PROP_HP", "statValue": 4780}, "reliquarySubstats": [{"appendPropId": "FIGHT_PROP_CHARGE_EFFICIENCY", "statValue": 27.2}, {"appendPropId": "FIGHT_PROP_CRITICAL_HURT", "statValue": 5.4}, {"appendPropId": "FIGHT_PROP_ATTACK_PERCENT", "statValue": 4.1}, {"appendPropId": "FIGHT_PROP_ATTACK", "statValue": 14}], "itemType": "ITEM_RELIQUARY", "icon": "UI_RelicIcon_15020_4", "equipType": "EQUIP_BRACER"}}, {"itemId": 94524, "reliquary": {"level": 21, "mainPropId": 12001, "appendPropIdList": [501063, 501204, 501082, 501224, 501204, 501222, 501201, 501061, 501222]}, "flat": {"nameTextMapHash": "481604708", "setNameTextMapHash": "2276480763", "rankLevel": 5, "reliquaryMainstat": {"mainPropId": "FIGHT_PROP_ATTACK", "statValue": 311}, "reliquarySubstats": [{"appendPropId": "FIGHT_PROP_ATTACK_PERCENT", "statValue": 9.3}, {"appendPropId": "FIGHT_PROP_CRITICAL", "statValue": 10.5}, {"appendPropId": "FIGHT_PROP_DEFENSE", "statValue": 19}, {"appendPropId": "FIGHT_PROP_CRITICAL_HURT", "statValue": 20.2}], "itemType": "ITEM_RELIQUARY", "icon": "UI_RelicIcon_15020_2", "equipType": "EQUIP_NECKLACE"}}, {"itemId": 96553, "reliquary": {"level": 21, "mainPropId": 10007, "appendPropIdList": [501054, 501064, 501224, 501031, 501221, 501223, 501223, 501054]}, "flat": {"nameTextMapHash": "452268540", "setNameTextMapHash": "1756609915", "rankLevel": 5, "reliquaryMainstat": {"mainPropId": "FIGHT_PROP_CHARGE_EFFICIENCY", "statValue": 51.8}, "reliquarySubstats": [{"appendPropId": "FIGHT_PROP_ATTACK", "statValue": 39}, {"appendPropId": "FIGHT_PROP_ATTACK_PERCENT", "statValue": 5.8}, {"appendPropId": "FIGHT_PROP_CRITICAL_HURT", "statValue": 27.2}, {"appendPropId": "FIGHT_PROP_HP_PERCENT", "statValue": 4.1}], "itemType": "ITEM_RELIQUARY", "icon": "UI_RelicIcon_15022_5", "equipType": "EQUIP_SHOES"}}, {"itemId": 94513, "reliquary": {"level": 21, "mainPropId": 15004, "appendPropIdList": [501203, 501222, 501052, 501232, 501051, 501204, 501233, 501201]}, "flat": {"nameTextMapHash": "3102891332", "setNameTextMapHash": "2276480763", "rankLevel": 5, "reliquaryMainstat": {"mainPropId": "FIGHT_PROP_ATTACK_PERCENT", "statValue": 46.6}, "reliquarySubstats": [{"appendPropId": "FIGHT_PROP_CRITICAL", "statValue": 10.1}, {"appendPropId": "FIGHT_PROP_CRITICAL_HURT", "statValue": 6.2}, {"appendPropId": "FIGHT_PROP_ATTACK", "statValue": 29}, {"appendPropId": "FIGHT_PROP_CHARGE_EFFICIENCY", "statValue": 11}], "itemType": "ITEM_RELIQUARY", "icon": "UI_RelicIcon_15020_1", "equipType": "EQUIP_RING"}}, {"itemId": 94533, "reliquary": {"level": 21, "mainPropId": 13008, "appendPropIdList": [501023, 501203, 501082, 501234, 501202, 501234, 501022, 501204]}, "flat": {"nameTextMapHash": "1804680132", "setNameTextMapHash": "2276480763", "rankLevel": 5, "reliquaryMainstat": {"mainPropId": "FIGHT_PROP_CRITICAL_HURT", "statValue": 62.2}, "reliquarySubstats": [{"appendPropId": "FIGHT_PROP_HP", "statValue": 508}, {"appendPropId": "FIGHT_PROP_CRITICAL", "statValue": 10.5}, {"appendPropId": "FIGHT_PROP_DEFENSE", "statValue": 19}, {"appendPropId": "FIGHT_PROP_CHARGE_EFFICIENCY", "statValue": 13}], "itemType": "ITEM_RELIQUARY", "icon": "UI_RelicIcon_15020_3", "equipType": "EQUIP_DRESS"}}, {"itemId": 13405, "weapon": {"level": 90, "promoteLevel": 6, "affixMap": {"113405": 3}}, "flat": {"nameTextMapHash": "4049410651", "rankLevel": 4, "weaponStats": [{"appendPropId": "FIGHT_PROP_BASE_ATTACK", "statValue": 454}, {"appendPropId": "FIGHT_PROP_CRITICAL", "statValue": 36.8}], "itemType": "ITEM_WEAPON", "icon": "UI_EquipIcon_Pole_Gladiator"}}], "fetterInfo": {"expLevel": 10}}, {"avatarId": 10000054, "propMap": {"1001": {"type": 1001, "ival": "0"}, "1002": {"type": 1002, "ival": "6", "val": "6"}, "1003": {"type": 1003, "ival": "0"}, "1004": {"type": 1004, "ival": "0"}, "4001": {"type": 4001, "ival": "90", "val": "90"}, "10010": {"type": 10010, "ival": "24000", "val": "24000"}}, "fightPropMap": {"1": 13470.501953125, "2": 7379.14013671875, "3": 1.8933600187301636, "4": 744.0007934570312, "5": 346.010009765625, "6": 0.09910000115633011, "7": 657.114013671875, "8": 118.05000305175781, "9": 0.13120000064373016, "20": -0.949999988079071, "21": 0, "22": 0.6865000128746033, "23": 1.194200038909912, "26": 0.909000039100647, "27": 0, "28": 0, "29": 0, "30": 0, "40": 0, "41": 0, "42": 0.2879999876022339, "43": 0, "44": 0, "45": 0, "46": 0, "50": 0, "51": 0, "52": 0, "53": 0, "54": 0, "55": 0, "56": 0, "72": 70, "1002": 70, "1010": 46354.15234375, "2000": 46354.15234375, "2001": 1163.7412109375, "2002": 861.3773193359375, "2003": 0}, "skillDepotId": 5401, "inherentProudSkillList": [542101, 542201, 542301, 542501], "skillLevelMap": {"10541": 1, "10542": 10, "10545": 7}, "equipList": [{"itemId": 74543, "reliquary": {"level": 21, "mainPropId": 14001, "appendPropIdList": [501064, 501054, 501033, 501221, 501034, 501032, 501061, 501032]}, "flat": {"nameTextMapHash": "2775020060", "setNameTextMapHash": "83115355", "rankLevel": 5, "reliquaryMainstat": {"mainPropId": "FIGHT_PROP_HP", "statValue": 4780}, "reliquarySubstats": [{"appendPropId": "FIGHT_PROP_ATTACK_PERCENT", "statValue": 9.9}, {"appendPropId": "FIGHT_PROP_ATTACK", "statValue": 19}, {"appendPropId": "FIGHT_PROP_HP_PERCENT", "statValue": 20.4}, {"appendPropId": "FIGHT_PROP_CRITICAL_HURT", "statValue": 5.4}], "itemType": "ITEM_RELIQUARY", "icon": "UI_RelicIcon_14004_4", "equipType": "EQUIP_BRACER"}}, {"itemId": 96523, "reliquary": {"level": 21, "mainPropId": 12001, "appendPropIdList": [501082, 501024, 501092, 501031, 501094, 501032, 501032, 501024]}, "flat": {"nameTextMapHash": "4122248468", "setNameTextMapHash": "1756609915", "rankLevel": 5, "reliquaryMainstat": {"mainPropId": "FIGHT_PROP_ATTACK", "statValue": 311}, "reliquarySubstats": [{"appendPropId": "FIGHT_PROP_DEFENSE", "statValue": 19}, {"appendPropId": "FIGHT_PROP_HP", "statValue": 598}, {"appendPropId": "FIGHT_PROP_DEFENSE_PERCENT", "statValue": 13.1}, {"appendPropId": "FIGHT_PROP_HP_PERCENT", "statValue": 13.4}], "itemType": "ITEM_RELIQUARY", "icon": "UI_RelicIcon_15022_2", "equipType": "EQUIP_NECKLACE"}}, {"itemId": 96553, "reliquary": {"level": 21, "mainPropId": 10002, "appendPropIdList": [501223, 501024, 501081, 501233, 501222, 501022, 501022, 501231]}, "flat": {"nameTextMapHash": "452268540", "setNameTextMapHash": "1756609915", "rankLevel": 5, "reliquaryMainstat": {"mainPropId": "FIGHT_PROP_HP_PERCENT", "statValue": 46.6}, "reliquarySubstats": [{"appendPropId": "FIGHT_PROP_CRITICAL_HURT", "statValue": 13.2}, {"appendPropId": "FIGHT_PROP_HP", "statValue": 777}, {"appendPropId": "FIGHT_PROP_DEFENSE", "statValue": 16}, {"appendPropId": "FIGHT_PROP_CHARGE_EFFICIENCY", "statValue": 10.4}], "itemType": "ITEM_RELIQUARY", "icon": "UI_RelicIcon_15022_5", "equipType": "EQUIP_SHOES"}}, {"itemId": 74513, "reliquary": {"level": 21, "mainPropId": 15002, "appendPropIdList": [501231, 501052, 501081, 501022, 501023, 501084, 501023, 501021]}, "flat": {"nameTextMapHash": "1841488868", "setNameTextMapHash": "83115355", "rankLevel": 5, "reliquaryMainstat": {"mainPropId": "FIGHT_PROP_HP_PERCENT", "statValue": 46.6}, "reliquarySubstats": [{"appendPropId": "FIGHT_PROP_CHARGE_EFFICIENCY", "statValue": 4.5}, {"appendPropId": "FIGHT_PROP_ATTACK", "statValue": 16}, {"appendPropId": "FIGHT_PROP_DEFENSE", "statValue": 39}, {"appendPropId": "FIGHT_PROP_HP", "statValue": 986}], "itemType": "ITEM_RELIQUARY", "icon": "UI_RelicIcon_14004_1", "equipType": "EQUIP_RING"}}, {"itemId": 97533, "reliquary": {"level": 21, "mainPropId": 13009, "appendPropIdList": [501033, 501083, 501231, 501022, 501034, 501084, 501031, 501034]}, "flat": {"nameTextMapHash": "2455573372", "setNameTextMapHash": "1558036915", "rankLevel": 5, "reliquaryMainstat": {"mainPropId": "FIGHT_PROP_HEAL_ADD", "statValue": 35.9}, "reliquarySubstats": [{"appendPropId": "FIGHT_PROP_HP_PERCENT", "statValue": 21}, {"appendPropId": "FIGHT_PROP_DEFENSE", "statValue": 44}, {"appendPropId": "FIGHT_PROP_CHARGE_EFFICIENCY", "statValue": 4.5}, {"appendPropId": "FIGHT_PROP_HP", "statValue": 239}], "itemType": "ITEM_RELIQUARY", "icon": "UI_RelicIcon_15023_3", "equipType": "EQUIP_DRESS"}}, {"itemId": 14406, "weapon": {"level": 90, "promoteLevel": 6, "affixMap": {"114406": 0}}, "flat": {"nameTextMapHash": "2521338131", "rankLevel": 4, "weaponStats": [{"appendPropId": "FIGHT_PROP_BASE_ATTACK", "statValue": 510}, {"appendPropId": "FIGHT_PROP_HP_PERCENT", "statValue": 41.3}], "itemType": "ITEM_WEAPON", "icon": "UI_EquipIcon_Catalyst_Proto"}}], "fetterInfo": {"expLevel": 10}}, {"avatarId": 10000037, "propMap": {"1001": {"type": 1001, "ival": "0"}, "1002": {"type": 1002, "ival": "6", "val": "6"}, "1003": {"type": 1003, "ival": "0"}, "1004": {"type": 1004, "ival": "0"}, "4001": {"type": 4001, "ival": "90", "val": "90"}, "10010": {"type": 10010, "ival": "24000", "val": "24000"}}, "fightPropMap": {"1": 9796.7294921875, "2": 5676.25, "4": 942.9243774414062, "5": 359.6400146484375, "6": 1.2069519758224487, "7": 630.214599609375, "8": 41.66999816894531, "9": 0.14579999446868896, "20": 0.3221000134944916, "21": 0, "22": 2.3917999267578125, "23": 1.2850000858306885, "26": 0, "27": 0, "28": 80, "29": 0, "30": 0, "40": 0, "41": 0, "42": 0, "43": 0, "44": 0, "45": 0, "46": 0.4659999907016754, "50": 0, "51": 0, "52": 0, "53": 0, "54": 0, "55": 0, "56": 0, "75": 60, "1005": 60, "1010": 15410.998046875, "2000": 15472.9794921875, "2001": 2440.62890625, "2002": 763.7698974609375, "2003": 0}, "skillDepotId": 3701, "inherentProudSkillList": [372101, 372201, 372301], "skillLevelMap": {"10371": 10, "10372": 6, "10373": 8}, "equipList": [{"itemId": 77544, "reliquary": {"level": 21, "mainPropId": 14001, "appendPropIdList": [501201, 501061, 501223, 501053, 501051, 501201, 501224, 501203, 501202]}, "flat": {"nameTextMapHash": "3221963316", "setNameTextMapHash": "147298547", "rankLevel": 5, "reliquaryMainstat": {"mainPropId": "FIGHT_PROP_HP", "statValue": 4780}, "reliquarySubstats": [{"appendPropId": "FIGHT_PROP_CRITICAL", "statValue": 12.1}, {"appendPropId": "FIGHT_PROP_ATTACK_PERCENT", "statValue": 4.1}, {"appendPropId": "FIGHT_PROP_CRITICAL_HURT", "statValue": 14.8}, {"appendPropId": "FIGHT_PROP_ATTACK", "statValue": 31}], "itemType": "ITEM_RELIQUARY", "icon": "UI_RelicIcon_15003_4", "equipType": "EQUIP_BRACER"}}, {"itemId": 77523, "reliquary": {"level": 21, "mainPropId": 12001, "appendPropIdList": [501232, 501084, 501202, 501222, 501224, 501234, 501223, 501231]}, "flat": {"nameTextMapHash": "369198060", "setNameTextMapHash": "147298547", "rankLevel": 5, "reliquaryMainstat": {"mainPropId": "FIGHT_PROP_ATTACK", "statValue": 311}, "reliquarySubstats": [{"appendPropId": "FIGHT_PROP_CHARGE_EFFICIENCY", "statValue": 16.2}, {"appendPropId": "FIGHT_PROP_DEFENSE", "statValue": 23}, {"appendPropId": "FIGHT_PROP_CRITICAL", "statValue": 3.1}, {"appendPropId": "FIGHT_PROP_CRITICAL_HURT", "statValue": 21}], "itemType": "ITEM_RELIQUARY", "icon": "UI_RelicIcon_15003_2", "equipType": "EQUIP_NECKLACE"}}, {"itemId": 77553, "reliquary": {"level": 21, "mainPropId": 10004, "appendPropIdList": [501053, 501203, 501224, 501024, 501224, 501224, 501024, 501224]}, "flat": {"nameTextMapHash": "3195328356", "setNameTextMapHash": "147298547", "rankLevel": 5, "reliquaryMainstat": {"mainPropId": "FIGHT_PROP_ATTACK_PERCENT", "statValue": 46.6}, "reliquarySubstats": [{"appendPropId": "FIGHT_PROP_ATTACK", "statValue": 18}, {"appendPropId": "FIGHT_PROP_CRITICAL", "statValue": 3.5}, {"appendPropId": "FIGHT_PROP_CRITICAL_HURT", "statValue": 31.1}, {"appendPropId": "FIGHT_PROP_HP", "statValue": 598}], "itemType": "ITEM_RELIQUARY", "icon": "UI_RelicIcon_15003_5", "equipType": "EQUIP_SHOES"}}, {"itemId": 71513, "reliquary": {"level": 21, "mainPropId": 15010, "appendPropIdList": [501082, 501062, 501224, 501233, 501234, 501064, 501222, 501224]}, "flat": {"nameTextMapHash": "3716289628", "setNameTextMapHash": "933076627", "rankLevel": 5, "reliquaryMainstat": {"mainPropId": "FIGHT_PROP_ICE_ADD_HURT", "statValue": 46.6}, "reliquarySubstats": [{"appendPropId": "FIGHT_PROP_DEFENSE", "statValue": 19}, {"appendPropId": "FIGHT_PROP_ATTACK_PERCENT", "statValue": 10.5}, {"appendPropId": "FIGHT_PROP_CRITICAL_HURT", "statValue": 21.8}, {"appendPropId": "FIGHT_PROP_CHARGE_EFFICIENCY", "statValue": 12.3}], "itemType": "ITEM_RELIQUARY", "icon": "UI_RelicIcon_14001_1", "equipType": "EQUIP_RING"}}, {"itemId": 77533, "reliquary": {"level": 21, "mainPropId": 13008, "appendPropIdList": [501202, 501024, 501062, 501094, 501201, 501201, 501063, 501094]}, "flat": {"nameTextMapHash": "2641672172", "setNameTextMapHash": "147298547", "rankLevel": 5, "reliquaryMainstat": {"mainPropId": "FIGHT_PROP_CRITICAL_HURT", "statValue": 62.2}, "reliquarySubstats": [{"appendPropId": "FIGHT_PROP_CRITICAL", "statValue": 8.6}, {"appendPropId": "FIGHT_PROP_HP", "statValue": 299}, {"appendPropId": "FIGHT_PROP_ATTACK_PERCENT", "statValue": 9.9}, {"appendPropId": "FIGHT_PROP_DEFENSE_PERCENT", "statValue": 14.6}], "itemType": "ITEM_RELIQUARY", "icon": "UI_RelicIcon_15003_3", "equipType": "EQUIP_DRESS"}}, {"itemId": 15502, "weapon": {"level": 90, "promoteLevel": 6, "affixMap": {"115502": 0}}, "flat": {"nameTextMapHash": "828711395", "rankLevel": 5, "weaponStats": [{"appendPropId": "FIGHT_PROP_BASE_ATTACK", "statValue": 608}, {"appendPropId": "FIGHT_PROP_ATTACK_PERCENT", "statValue": 49.6}], "itemType": "ITEM_WEAPON", "icon": "UI_EquipIcon_Bow_Amos"}}], "fetterInfo": {"expLevel": 10}}, {"avatarId": 10000031, "propMap": {"1001": {"type": 1001, "ival": "68228", "val": "68228"}, "1002": {"type": 1002, "ival": "3", "val": "3"}, "1003": {"type": 1003, "ival": "0"}, "1004": {"type": 1004, "ival": "0"}, "4001": {"type": 4001, "ival": "59", "val": "59"}, "10010": {"type": 10010, "ival": "24000", "val": "24000"}}, "talentIdList": [311, 312], "fightPropMap": {"1": 5990.03173828125, "2": 5048.8798828125, "4": 767.2928466796875, "5": 355.739990234375, "6": 1.2375000715255737, "7": 387.0634765625, "8": 41.65999984741211, "9": 0.07289999723434448, "20": 0.6685680150985718, "21": 0, "22": 2.0077998638153076, "23": 1.155400037765503, "26": 0, "27": 0, "28": 139.8699951171875, "29": 0, "30": 0, "40": 0, "41": 0.4659999907016754, "42": 0, "43": 0, "44": 0, "45": 0, "46": 0, "50": 0, "51": 0, "52": 0, "53": 0, "54": 0, "55": 0, "56": 0, "71": 60, "1001": 34.430912017822266, "1010": 8174.03076171875, "2000": 11038.912109375, "2001": 2072.557861328125, "2002": 456.9404296875, "2003": 0, "3007": 0, "3015": 0, "3016": 0, "3017": 0, "3018": 0, "3019": 0, "3020": 0, "3021": 0}, "skillDepotId": 3101, "inherentProudSkillList": [312101, 312301], "skillLevelMap": {"10311": 4, "10312": 4, "10313": 4}, "equipList": [{"itemId": 75543, "reliquary": {"level": 21, "mainPropId": 14001, "appendPropIdList": [501063, 501094, 501203, 501223, 501063, 501224, 501224, 501203]}, "flat": {"nameTextMapHash": "2229209884", "setNameTextMapHash": "1212345779", "rankLevel": 5, "reliquaryMainstat": {"mainPropId": "FIGHT_PROP_HP", "statValue": 4780}, "reliquarySubstats": [{"appendPropId": "FIGHT_PROP_ATTACK_PERCENT", "statValue": 10.5}, {"appendPropId": "FIGHT_PROP_DEFENSE_PERCENT", "statValue": 7.3}, {"appendPropId": "FIGHT_PROP_CRITICAL", "statValue": 7}, {"appendPropId": "FIGHT_PROP_CRITICAL_HURT", "statValue": 22.5}], "itemType": "ITEM_RELIQUARY", "icon": "UI_RelicIcon_15001_4", "equipType": "EQUIP_BRACER"}}, {"itemId": 75524, "reliquary": {"level": 21, "mainPropId": 12001, "appendPropIdList": [501241, 501222, 501023, 501204, 501204, 501241, 501223, 501224, 501243]}, "flat": {"nameTextMapHash": "1359349548", "setNameTextMapHash": "1212345779", "rankLevel": 5, "reliquaryMainstat": {"mainPropId": "FIGHT_PROP_ATTACK", "statValue": 311}, "reliquarySubstats": [{"appendPropId": "FIGHT_PROP_ELEMENT_MASTERY", "statValue": 54}, {"appendPropId": "FIGHT_PROP_CRITICAL_HURT", "statValue": 21}, {"appendPropId": "FIGHT_PROP_HP", "statValue": 269}, {"appendPropId": "FIGHT_PROP_CRITICAL", "statValue": 7.8}], "itemType": "ITEM_RELIQUARY", "icon": "UI_RelicIcon_15001_2", "equipType": "EQUIP_NECKLACE"}}, {"itemId": 77554, "reliquary": {"level": 21, "mainPropId": 10004, "appendPropIdList": [501244, 501203, 501083, 501224, 501224, 501243, 501243, 501222, 501243]}, "flat": {"nameTextMapHash": "744414012", "setNameTextMapHash": "147298547", "rankLevel": 5, "reliquaryMainstat": {"mainPropId": "FIGHT_PROP_ATTACK_PERCENT", "statValue": 46.6}, "reliquarySubstats": [{"appendPropId": "FIGHT_PROP_ELEMENT_MASTERY", "statValue": 86}, {"appendPropId": "FIGHT_PROP_CRITICAL", "statValue": 3.5}, {"appendPropId": "FIGHT_PROP_DEFENSE", "statValue": 21}, {"appendPropId": "FIGHT_PROP_CRITICAL_HURT", "statValue": 21.8}], "itemType": "ITEM_RELIQUARY", "icon": "UI_RelicIcon_15003_5", "equipType": "EQUIP_SHOES"}}, {"itemId": 93513, "reliquary": {"level": 21, "mainPropId": 15009, "appendPropIdList": [501224, 501063, 501083, 501052, 501062, 501224, 501224, 501051]}, "flat": {"nameTextMapHash": "2718771884", "setNameTextMapHash": "4144069251", "rankLevel": 5, "reliquaryMainstat": {"mainPropId": "FIGHT_PROP_ELEC_ADD_HURT", "statValue": 46.6}, "reliquarySubstats": [{"appendPropId": "FIGHT_PROP_CRITICAL_HURT", "statValue": 23.3}, {"appendPropId": "FIGHT_PROP_ATTACK_PERCENT", "statValue": 9.9}, {"appendPropId": "FIGHT_PROP_DEFENSE", "statValue": 21}, {"appendPropId": "FIGHT_PROP_ATTACK", "statValue": 29}], "itemType": "ITEM_RELIQUARY", "icon": "UI_RelicIcon_15019_1", "equipType": "EQUIP_RING"}}, {"itemId": 93534, "reliquary": {"level": 21, "mainPropId": 13008, "appendPropIdList": [501203, 501061, 501234, 501052, 501231, 501231, 501202, 501062, 501204]}, "flat": {"nameTextMapHash": "259640420", "setNameTextMapHash": "4144069251", "rankLevel": 5, "reliquaryMainstat": {"mainPropId": "FIGHT_PROP_CRITICAL_HURT", "statValue": 62.2}, "reliquarySubstats": [{"appendPropId": "FIGHT_PROP_CRITICAL", "statValue": 10.5}, {"appendPropId": "FIGHT_PROP_ATTACK_PERCENT", "statValue": 8.7}, {"appendPropId": "FIGHT_PROP_CHARGE_EFFICIENCY", "statValue": 15.5}, {"appendPropId": "FIGHT_PROP_ATTACK", "statValue": 16}], "itemType": "ITEM_RELIQUARY", "icon": "UI_RelicIcon_15019_3", "equipType": "EQUIP_DRESS"}}, {"itemId": 15507, "weapon": {"level": 90, "promoteLevel": 6, "affixMap": {"115507": 0}}, "flat": {"nameTextMapHash": "1901973075", "rankLevel": 5, "weaponStats": [{"appendPropId": "FIGHT_PROP_BASE_ATTACK", "statValue": 608}, {"appendPropId": "FIGHT_PROP_CRITICAL", "statValue": 33.1}], "itemType": "ITEM_WEAPON", "icon": "UI_EquipIcon_Bow_Worldbane"}}], "fetterInfo": {"expLevel": 2}, "costumeId": 203101}, {"avatarId": 10000002, "propMap": {"1001": {"type": 1001, "ival": "28074", "val": "28074"}, "1002": {"type": 1002, "ival": "6", "val": "6"}, "1003": {"type": 1003, "ival": "0"}, "1004": {"type": 1004, "ival": "0"}, "4001": {"type": 4001, "ival": "88", "val": "88"}, "10010": {"type": 10010, "ival": "24000", "val": "24000"}}, "fightPropMap": {"1": 12677.0283203125, "2": 5795.759765625, "3": 0.14569999277591705, "4": 1011.5401611328125, "5": 340.17999267578125, "6": 0.9325000047683716, "7": 772.879638671875, "8": 55.55000305175781, "9": 0.15299999713897705, "20": 0.1899999976158142, "21": 0, "22": 2.9028241634368896, "23": 1.0906000137329102, "26": 0, "27": 0, "28": 0, "29": 0, "30": 0, "40": 0, "41": 0, "42": 0, "43": 0, "44": 0, "45": 0, "46": 0.6159999966621399, "50": 0, "51": 0, "52": 0, "53": 0, "54": 0, "55": 0, "56": 0, "75": 80, "1005": 57.09375762939453, "1010": 16317.392578125, "2000": 20319.83203125, "2001": 2294.9814453125, "2002": 946.6802368164062, "2003": 0, "3007": 0, "3008": 0, "3009": 0, "3010": 0, "3011": 0, "3012": 0, "3013": 0, "3014": 0, "3015": 0, "3016": 0, "3017": 0, "3018": 0, "3019": 0, "3020": 0, "3021": 0}, "skillDepotId": 201, "inherentProudSkillList": [22101, 22201, 22301], "skillLevelMap": {"10013": 1, "10018": 6, "10019": 9, "10024": 8}, "equipList": [{"itemId": 71543, "reliquary": {"level": 21, "mainPropId": 14001, "appendPropIdList": [501051, 501084, 501224, 501063, 501221, 501223, 501064, 501222]}, "flat": {"nameTextMapHash": "4088170252", "setNameTextMapHash": "933076627", "rankLevel": 5, "reliquaryMainstat": {"mainPropId": "FIGHT_PROP_HP", "statValue": 4780}, "reliquarySubstats": [{"appendPropId": "FIGHT_PROP_ATTACK", "statValue": 14}, {"appendPropId": "FIGHT_PROP_DEFENSE", "statValue": 23}, {"appendPropId": "FIGHT_PROP_CRITICAL_HURT", "statValue": 26.4}, {"appendPropId": "FIGHT_PROP_ATTACK_PERCENT", "statValue": 11.1}], "itemType": "ITEM_RELIQUARY", "icon": "UI_RelicIcon_14001_4", "equipType": "EQUIP_BRACER"}}, {"itemId": 71524, "reliquary": {"level": 21, "mainPropId": 12001, "appendPropIdList": [501021, 501064, 501032, 501224, 501224, 501223, 501033, 501063, 501023]}, "flat": {"nameTextMapHash": "2098993868", "setNameTextMapHash": "933076627", "rankLevel": 5, "reliquaryMainstat": {"mainPropId": "FIGHT_PROP_ATTACK", "statValue": 311}, "reliquarySubstats": [{"appendPropId": "FIGHT_PROP_HP", "statValue": 478}, {"appendPropId": "FIGHT_PROP_ATTACK_PERCENT", "statValue": 11.1}, {"appendPropId": "FIGHT_PROP_HP_PERCENT", "statValue": 9.9}, {"appendPropId": "FIGHT_PROP_CRITICAL_HURT", "statValue": 22.5}], "itemType": "ITEM_RELIQUARY", "icon": "UI_RelicIcon_14001_2", "equipType": "EQUIP_NECKLACE"}}, {"itemId": 71554, "reliquary": {"level": 21, "mainPropId": 10004, "appendPropIdList": [501052, 501091, 501224, 501231, 501091, 501091, 501224, 501221, 501231]}, "flat": {"nameTextMapHash": "2835521076", "setNameTextMapHash": "933076627", "rankLevel": 5, "reliquaryMainstat": {"mainPropId": "FIGHT_PROP_ATTACK_PERCENT", "statValue": 46.6}, "reliquarySubstats": [{"appendPropId": "FIGHT_PROP_ATTACK", "statValue": 16}, {"appendPropId": "FIGHT_PROP_DEFENSE_PERCENT", "statValue": 15.3}, {"appendPropId": "FIGHT_PROP_CRITICAL_HURT", "statValue": 21}, {"appendPropId": "FIGHT_PROP_CHARGE_EFFICIENCY", "statValue": 9.1}], "itemType": "ITEM_RELIQUARY", "icon": "UI_RelicIcon_14001_5", "equipType": "EQUIP_SHOES"}}, {"itemId": 95514, "reliquary": {"level": 21, "mainPropId": 15010, "appendPropIdList": [501022, 501222, 501201, 501063, 501221, 501203, 501224, 501024, 501222]}, "flat": {"nameTextMapHash": "1544958028", "setNameTextMapHash": "2546254811", "rankLevel": 5, "reliquaryMainstat": {"mainPropId": "FIGHT_PROP_ICE_ADD_HURT", "statValue": 46.6}, "reliquarySubstats": [{"appendPropId": "FIGHT_PROP_HP", "statValue": 538}, {"appendPropId": "FIGHT_PROP_CRITICAL_HURT", "statValue": 25.7}, {"appendPropId": "FIGHT_PROP_CRITICAL", "statValue": 6.2}, {"appendPropId": "FIGHT_PROP_ATTACK_PERCENT", "statValue": 5.3}], "itemType": "ITEM_RELIQUARY", "icon": "UI_RelicIcon_15021_1", "equipType": "EQUIP_RING"}}, {"itemId": 71534, "reliquary": {"level": 21, "mainPropId": 13008, "appendPropIdList": [501032, 501061, 501204, 501081, 501064, 501063, 501081, 501204, 501061]}, "flat": {"nameTextMapHash": "2853313156", "setNameTextMapHash": "933076627", "rankLevel": 5, "reliquaryMainstat": {"mainPropId": "FIGHT_PROP_CRITICAL_HURT", "statValue": 62.2}, "reliquarySubstats": [{"appendPropId": "FIGHT_PROP_HP_PERCENT", "statValue": 4.7}, {"appendPropId": "FIGHT_PROP_ATTACK_PERCENT", "statValue": 19.2}, {"appendPropId": "FIGHT_PROP_CRITICAL", "statValue": 7.8}, {"appendPropId": "FIGHT_PROP_DEFENSE", "statValue": 32}], "itemType": "ITEM_RELIQUARY", "icon": "UI_RelicIcon_14001_3", "equipType": "EQUIP_DRESS"}}, {"itemId": 11509, "weapon": {"level": 90, "promoteLevel": 6, "affixMap": {"111509": 0}}, "flat": {"nameTextMapHash": "4124851547", "rankLevel": 5, "weaponStats": [{"appendPropId": "FIGHT_PROP_BASE_ATTACK", "statValue": 674}, {"appendPropId": "FIGHT_PROP_CRITICAL_HURT", "statValue": 44.1}], "itemType": "ITEM_WEAPON", "icon": "UI_EquipIcon_Sword_Narukami"}}], "fetterInfo": {"expLevel": 10}}, {"avatarId": 10000030, "propMap": {"1001": {"type": 1001, "ival": "0"}, "1002": {"type": 1002, "ival": "6", "val": "6"}, "1003": {"type": 1003, "ival": "0"}, "1004": {"type": 1004, "ival": "0"}, "4001": {"type": 4001, "ival": "90", "val": "90"}, "10010": {"type": 10010, "ival": "24000", "val": "24000"}}, "fightPropMap": {"1": 14695.09375, "2": 6243.8896484375, "3": 0.7982999682426453, "4": 859.2119140625, "5": 349.9000244140625, "6": 0.9086520075798035, "7": 737.8121948242188, "8": 37.040000915527344, "9": 0.07289999723434448, "20": 0.36500000953674316, "21": 0, "22": 1.9688999652862549, "23": 1, "26": 0, "27": 0, "28": 23.309999465942383, "29": 0, "30": 0, "40": 0, "41": 0, "42": 0, "43": 0, "44": 0, "45": 0.7539999485015869, "46": 0, "50": 0, "51": 0, "52": 0, "53": 0, "54": 0, "55": 0, "56": 0, "76": 40, "81": 0.20000000298023224, "1006": 40, "1010": 32670.078125, "2000": 32670.078125, "2001": 1989.836669921875, "2002": 828.6387329101562, "2003": 0, "3007": 0, "3015": 0, "3016": 0, "3017": 0, "3018": 0, "3019": 0, "3020": 0, "3021": 0}, "skillDepotId": 3001, "inherentProudSkillList": [302101, 302201, 302301], "skillLevelMap": {"10301": 6, "10302": 10, "10303": 8}, "equipList": [{"itemId": 98543, "reliquary": {"level": 21, "mainPropId": 14001, "appendPropIdList": [501223, 501082, 501054, 501203, 501202, 501082, 501224, 501223]}, "flat": {"nameTextMapHash": "752364252", "setNameTextMapHash": "3626268211", "rankLevel": 5, "reliquaryMainstat": {"mainPropId": "FIGHT_PROP_HP", "statValue": 4780}, "reliquarySubstats": [{"appendPropId": "FIGHT_PROP_CRITICAL_HURT", "statValue": 21.8}, {"appendPropId": "FIGHT_PROP_DEFENSE", "statValue": 37}, {"appendPropId": "FIGHT_PROP_ATTACK", "statValue": 19}, {"appendPropId": "FIGHT_PROP_CRITICAL", "statValue": 6.6}], "itemType": "ITEM_RELIQUARY", "icon": "UI_RelicIcon_15024_4", "equipType": "EQUIP_BRACER"}}, {"itemId": 75524, "reliquary": {"level": 21, "mainPropId": 12001, "appendPropIdList": [501204, 501024, 501221, 501032, 501224, 501033, 501203, 501203, 501031]}, "flat": {"nameTextMapHash": "1359349548", "setNameTextMapHash": "1212345779", "rankLevel": 5, "reliquaryMainstat": {"mainPropId": "FIGHT_PROP_ATTACK", "statValue": 311}, "reliquarySubstats": [{"appendPropId": "FIGHT_PROP_CRITICAL", "statValue": 10.9}, {"appendPropId": "FIGHT_PROP_HP", "statValue": 299}, {"appendPropId": "FIGHT_PROP_CRITICAL_HURT", "statValue": 13.2}, {"appendPropId": "FIGHT_PROP_HP_PERCENT", "statValue": 14}], "itemType": "ITEM_RELIQUARY", "icon": "UI_RelicIcon_15001_2", "equipType": "EQUIP_NECKLACE"}}, {"itemId": 93553, "reliquary": {"level": 21, "mainPropId": 10002, "appendPropIdList": [501054, 501224, 501063, 501204, 501202, 501223, 501222, 501224]}, "flat": {"nameTextMapHash": "2767946268", "setNameTextMapHash": "4144069251", "rankLevel": 5, "reliquaryMainstat": {"mainPropId": "FIGHT_PROP_HP_PERCENT", "statValue": 46.6}, "reliquarySubstats": [{"appendPropId": "FIGHT_PROP_ATTACK", "statValue": 19}, {"appendPropId": "FIGHT_PROP_CRITICAL_HURT", "statValue": 28.8}, {"appendPropId": "FIGHT_PROP_ATTACK_PERCENT", "statValue": 5.3}, {"appendPropId": "FIGHT_PROP_CRITICAL", "statValue": 7}], "itemType": "ITEM_RELIQUARY", "icon": "UI_RelicIcon_15019_5", "equipType": "EQUIP_SHOES"}}, {"itemId": 98513, "reliquary": {"level": 21, "mainPropId": 15013, "appendPropIdList": [501022, 501224, 501031, 501244, 501222, 501021, 501223, 501022]}, "flat": {"nameTextMapHash": "1717571964", "setNameTextMapHash": "3626268211", "rankLevel": 5, "reliquaryMainstat": {"mainPropId": "FIGHT_PROP_ROCK_ADD_HURT", "statValue": 46.6}, "reliquarySubstats": [{"appendPropId": "FIGHT_PROP_HP", "statValue": 687}, {"appendPropId": "FIGHT_PROP_CRITICAL_HURT", "statValue": 21}, {"appendPropId": "FIGHT_PROP_HP_PERCENT", "statValue": 4.1}, {"appendPropId": "FIGHT_PROP_ELEMENT_MASTERY", "statValue": 23}], "itemType": "ITEM_RELIQUARY", "icon": "UI_RelicIcon_15024_1", "equipType": "EQUIP_RING"}}, {"itemId": 93533, "reliquary": {"level": 21, "mainPropId": 13008, "appendPropIdList": [501031, 501021, 501094, 501204, 501202, 501033, 501023, 501034]}, "flat": {"nameTextMapHash": "2650209148", "setNameTextMapHash": "4144069251", "rankLevel": 5, "reliquaryMainstat": {"mainPropId": "FIGHT_PROP_CRITICAL_HURT", "statValue": 62.2}, "reliquarySubstats": [{"appendPropId": "FIGHT_PROP_HP_PERCENT", "statValue": 15.2}, {"appendPropId": "FIGHT_PROP_HP", "statValue": 478}, {"appendPropId": "FIGHT_PROP_DEFENSE_PERCENT", "statValue": 7.3}, {"appendPropId": "FIGHT_PROP_CRITICAL", "statValue": 7}], "itemType": "ITEM_RELIQUARY", "icon": "UI_RelicIcon_15019_3", "equipType": "EQUIP_DRESS"}}, {"itemId": 13504, "weapon": {"level": 90, "promoteLevel": 6, "affixMap": {"113504": 0}}, "flat": {"nameTextMapHash": "197755235", "rankLevel": 5, "weaponStats": [{"appendPropId": "FIGHT_PROP_BASE_ATTACK", "statValue": 608}, {"appendPropId": "FIGHT_PROP_ATTACK_PERCENT", "statValue": 49.6}], "itemType": "ITEM_WEAPON", "icon": "UI_EquipIcon_Pole_Kunwu"}}], "fetterInfo": {"expLevel": 10}}, {"avatarId": 10000066, "propMap": {"1001": {"type": 1001, "ival": "14054", "val": "14054"}, "1002": {"type": 1002, "ival": "6", "val": "6"}, "1003": {"type": 1003, "ival": "0"}, "1004": {"type": 1004, "ival": "0"}, "4001": {"type": 4001, "ival": "89", "val": "89"}, "10010": {"type": 10010, "ival": "24000", "val": "24000"}}, "fightPropMap": {"1": 13619.3251953125, "2": 6363.3896484375, "3": 0.19820000231266022, "4": 806.4841918945312, "5": 359.6400146484375, "6": 0.6460000276565552, "7": 763.169677734375, "9": 0.11659999936819077, "20": 0.5278399586677551, "21": 0, "22": 2.5083999633789062, "23": 1.207200050354004, "26": 0, "27": 0, "28": 62.94000244140625, "29": 0, "30": 0, "40": 0, "41": 0, "42": 0.4659999907016754, "43": 0, "44": 0, "45": 0, "46": 0, "50": 0, "51": 0, "52": 0, "53": 0, "54": 0, "55": 0, "56": 0, "72": 80, "1002": 80, "1010": 22682.064453125, "2000": 22682.064453125, "2001": 1687.113037109375, "2002": 852.1552734375, "2003": 0}, "skillDepotId": 6601, "inherentProudSkillList": [662101, 662201, 662301], "skillLevelMap": {"10661": 3, "10662": 9, "10665": 7}, "equipList": [{"itemId": 80543, "reliquary": {"level": 21, "mainPropId": 14001, "appendPropIdList": [501034, 501232, 501222, 501053, 501223, 501222, 501051, 501221]}, "flat": {"nameTextMapHash": "1149648428", "setNameTextMapHash": "1524173875", "rankLevel": 5, "reliquaryMainstat": {"mainPropId": "FIGHT_PROP_HP", "statValue": 4780}, "reliquarySubstats": [{"appendPropId": "FIGHT_PROP_HP_PERCENT", "statValue": 5.8}, {"appendPropId": "FIGHT_PROP_CHARGE_EFFICIENCY", "statValue": 5.2}, {"appendPropId": "FIGHT_PROP_CRITICAL_HURT", "statValue": 24.9}, {"appendPropId": "FIGHT_PROP_ATTACK", "statValue": 31}], "itemType": "ITEM_RELIQUARY", "icon": "UI_RelicIcon_15006_4", "equipType": "EQUIP_BRACER"}}, {"itemId": 75524, "reliquary": {"level": 21, "mainPropId": 12001, "appendPropIdList": [501223, 501093, 501204, 501022, 501204, 501222, 501202, 501223, 501222]}, "flat": {"nameTextMapHash": "1359349548", "setNameTextMapHash": "1212345779", "rankLevel": 5, "reliquaryMainstat": {"mainPropId": "FIGHT_PROP_ATTACK", "statValue": 311}, "reliquarySubstats": [{"appendPropId": "FIGHT_PROP_CRITICAL_HURT", "statValue": 26.4}, {"appendPropId": "FIGHT_PROP_DEFENSE_PERCENT", "statValue": 6.6}, {"appendPropId": "FIGHT_PROP_CRITICAL", "statValue": 10.9}, {"appendPropId": "FIGHT_PROP_HP", "statValue": 239}], "itemType": "ITEM_RELIQUARY", "icon": "UI_RelicIcon_15001_2", "equipType": "EQUIP_NECKLACE"}}, {"itemId": 75554, "reliquary": {"level": 21, "mainPropId": 10004, "appendPropIdList": [501031, 501022, 501224, 501232, 501224, 501034, 501221, 501223, 501031]}, "flat": {"nameTextMapHash": "1021872964", "setNameTextMapHash": "1212345779", "rankLevel": 5, "reliquaryMainstat": {"mainPropId": "FIGHT_PROP_ATTACK_PERCENT", "statValue": 46.6}, "reliquarySubstats": [{"appendPropId": "FIGHT_PROP_HP_PERCENT", "statValue": 14}, {"appendPropId": "FIGHT_PROP_HP", "statValue": 239}, {"appendPropId": "FIGHT_PROP_CRITICAL_HURT", "statValue": 28}, {"appendPropId": "FIGHT_PROP_CHARGE_EFFICIENCY", "statValue": 5.2}], "itemType": "ITEM_RELIQUARY", "icon": "UI_RelicIcon_15001_5", "equipType": "EQUIP_SHOES"}}, {"itemId": 97513, "reliquary": {"level": 21, "mainPropId": 15011, "appendPropIdList": [501224, 501233, 501024, 501091, 501023, 501224, 501221, 501231]}, "flat": {"nameTextMapHash": "1349121996", "setNameTextMapHash": "1558036915", "rankLevel": 5, "reliquaryMainstat": {"mainPropId": "FIGHT_PROP_WATER_ADD_HURT", "statValue": 46.6}, "reliquarySubstats": [{"appendPropId": "FIGHT_PROP_CRITICAL_HURT", "statValue": 21}, {"appendPropId": "FIGHT_PROP_CHARGE_EFFICIENCY", "statValue": 10.4}, {"appendPropId": "FIGHT_PROP_HP", "statValue": 568}, {"appendPropId": "FIGHT_PROP_DEFENSE_PERCENT", "statValue": 5.1}], "itemType": "ITEM_RELIQUARY", "icon": "UI_RelicIcon_15023_1", "equipType": "EQUIP_RING"}}, {"itemId": 75534, "reliquary": {"level": 21, "mainPropId": 13008, "appendPropIdList": [501053, 501023, 501244, 501201, 501204, 501023, 501243, 501201, 501242]}, "flat": {"nameTextMapHash": "1855279292", "setNameTextMapHash": "1212345779", "rankLevel": 5, "reliquaryMainstat": {"mainPropId": "FIGHT_PROP_CRITICAL_HURT", "statValue": 62.2}, "reliquarySubstats": [{"appendPropId": "FIGHT_PROP_ATTACK", "statValue": 18}, {"appendPropId": "FIGHT_PROP_HP", "statValue": 538}, {"appendPropId": "FIGHT_PROP_ELEMENT_MASTERY", "statValue": 63}, {"appendPropId": "FIGHT_PROP_CRITICAL", "statValue": 9.3}], "itemType": "ITEM_RELIQUARY", "icon": "UI_RelicIcon_15001_3", "equipType": "EQUIP_DRESS"}}, {"itemId": 11409, "weapon": {"level": 90, "promoteLevel": 6, "affixMap": {"111409": 0}}, "flat": {"nameTextMapHash": "3796905611", "rankLevel": 4, "weaponStats": [{"appendPropId": "FIGHT_PROP_BASE_ATTACK", "statValue": 510}, {"appendPropId": "FIGHT_PROP_CRITICAL", "statValue": 27.6}], "itemType": "ITEM_WEAPON", "icon": "UI_EquipIcon_Sword_Bloodstained"}}], "fetterInfo": {"expLevel": 10}}], "ttl": 300}