{"playerUid": "100844614", "playerName": "大世界7倒计时", "avatarId": 10000066, "avatarName": "神里绫人", "avatarFetter": 10, "avatarLevel": "20", "avatarElement": "Hydro", "dataTime": "2022-08-21 02:30:27", "avatarSkill": [{"skillId": "10661", "skillName": "普通攻击·神里流·转", "skillLevel": 1, "skillIcon": "Skill_A_01"}, {"skillId": "10662", "skillName": "神里流·镜花", "skillLevel": 1, "skillIcon": "Skill_S_Ayato_01"}, {"skillId": "10665", "skillName": "神里流·水囿", "skillLevel": 1, "skillIcon": "Skill_E_Ayato_01"}], "avatarEnName": "Ayato", "talentList": [], "avatarFightProp": {"hp": 3685.133544921875, "baseHp": 3685.133544921875, "addHp": 0.0, "atk": 103.57510375976562, "baseAtk": 103.57510375976562, "addAtk": 0.0, "def": 206.49903869628906, "baseDef": 206.49903869628906, "addDef": 0.0, "elementalMastery": 0, "critRate": 0.05000000074505806, "critDmg": 0.5, "energyRecharge": 1, "healBonus": 0, "healedBonus": 0, "physicalDmgSub": 0, "physicalDmgBonus": 0, "dmgBonus": 0}, "weaponInfo": {"itemId": 11101, "nameTextMapHash": "2410593283", "weaponIcon": "UI_EquipIcon_Sword_Blunt", "weaponType": "单手剑", "weaponName": "无锋剑", "weaponStar": 1, "promoteLevel": 0, "weaponLevel": 1, "weaponAffix": 1, "weaponStats": [{"appendPropId": "FIGHT_PROP_BASE_ATTACK", "statName": "基础攻击力", "statValue": 23}], "weaponEffect": ""}, "equipSets": {"type": "", "set": ""}, "equipList": []}