{"nickname": "伊卡洛斯", "level": 60, "signature": "好起来了？", "worldLevel": 8, "nameCardId": 210059, "finishAchievementNum": 555, "towerFloorIndex": 8, "towerLevelIndex": 3, "showAvatarInfoList": [{"avatarId": 10000042, "level": 90, "costumeId": 204201}, {"avatarId": 10000029, "level": 90}, {"avatarId": 10000016, "level": 90}, {"avatarId": 10000046, "level": 90}, {"avatarId": 10000027, "level": 90, "costumeId": 202701}, {"avatarId": 10000032, "level": 90}, {"avatarId": 10000039, "level": 80}, {"avatarId": 10000065, "level": 90}], "showNameCardIdList": [210004, 210019, 210043, 210020, 210038, 210009, 210024, 210025, 210053], "profilePicture": {"avatarId": 10000046}}