{"playerUid": "100454009", "playerName": "cqdngtd", "avatarId": 10000035, "avatarName": "七七", "avatarFetter": 10, "avatarLevel": "90", "avatarElement": "Cryo", "dataTime": "2022-08-20 02:51:18", "avatarSkill": [{"skillId": "10351", "skillName": "普通攻击·云来古剑法", "skillLevel": 8, "skillIcon": "Skill_A_01"}, {"skillId": "10352", "skillName": "仙法·寒病鬼差", "skillLevel": 8, "skillIcon": "Skill_S_Qiqi_01"}, {"skillId": "10353", "skillName": "仙法·救苦度厄", "skillLevel": 8, "skillIcon": "Skill_E_Qiqi_01"}], "avatarEnName": "Qiqi", "talentList": [{"talentId": 351, "talentName": "寒苦回向", "talentIcon": "UI_Talent_S_Qiqi_01"}, {"talentId": 352, "talentName": "冰寒蚀骨", "talentIcon": "UI_Talent_S_Qiqi_02"}, {"talentId": 353, "talentName": "升天宝诰", "talentIcon": "UI_Talent_U_Qiqi_01"}], "avatarFightProp": {"hp": 12368.37109375, "baseHp": 12368.37109375, "addHp": 0.0, "atk": 579.6361083984375, "baseAtk": 579.6361083984375, "addAtk": 0.0, "def": 922.2652587890625, "baseDef": 922.2652587890625, "addDef": 0.0, "elementalMastery": 0, "critRate": 0.05000000074505806, "critDmg": 0.5, "energyRecharge": 1.4510655403137207, "healBonus": 0.2214999943971634, "healedBonus": 0, "physicalDmgSub": 0, "physicalDmgBonus": 0, "dmgBonus": 0}, "weaponInfo": {"itemId": 11401, "nameTextMapHash": "2474354867", "weaponIcon": "UI_EquipIcon_Sword_Zephyrus", "weaponType": "单手剑", "weaponName": "西风剑", "weaponStar": 4, "promoteLevel": 3, "weaponLevel": 60, "weaponAffix": 5, "weaponStats": [{"appendPropId": "FIGHT_PROP_BASE_ATTACK", "statName": "基础攻击力", "statValue": 293}, {"appendPropId": "FIGHT_PROP_CHARGE_EFFICIENCY", "statName": "元素充能效率", "statValue": 45.1}], "weaponEffect": "攻击造成暴击时，有100%的几率产生少量元素微粒，能为角色恢复6点元素能量。该效果每6秒只能触发一次。"}, "equipSets": {"type": "", "set": ""}, "equipList": []}