{"nickname": "默默", "level": 58, "worldLevel": 8, "nameCardId": 210112, "finishAchievementNum": 430, "towerFloorIndex": 12, "towerLevelIndex": 3, "showAvatarInfoList": [{"avatarId": 10000046, "level": 90}, {"avatarId": 10000052, "level": 90}, {"avatarId": 10000002, "level": 90}, {"avatarId": 10000060, "level": 90}, {"avatarId": 10000047, "level": 90}, {"avatarId": 10000058, "level": 81}, {"avatarId": 10000030, "level": 81}, {"avatarId": 10000025, "level": 80}], "showNameCardIdList": [210059, 210081, 210092, 210082, 210018, 210016, 210009], "profilePicture": {"avatarId": 10000047}}