{"nickname": "氿", "level": 55, "signature": "雷神老婆申鹤老婆绫人老公一斗老公我都要贴贴～～", "worldLevel": 8, "nameCardId": 210092, "finishAchievementNum": 384, "towerFloorIndex": 8, "towerLevelIndex": 3, "showAvatarInfoList": [{"avatarId": 10000052, "level": 80}, {"avatarId": 10000026, "level": 89}, {"avatarId": 10000066, "level": 80}, {"avatarId": 10000030, "level": 88}, {"avatarId": 10000035, "level": 80}, {"avatarId": 10000043, "level": 88}], "showNameCardIdList": [210058, 210044, 210019], "profilePicture": {"avatarId": 10000052}}