{"playerUid": "181761689", "playerName": "枫原万叶", "avatarId": 10000050, "avatarName": "托马", "avatarFetter": 1, "avatarLevel": "20", "avatarElement": "Pyro", "dataTime": "2022-08-04 02:39:24", "avatarSkill": [{"skillId": "10501", "skillName": "普通攻击·迅破枪势", "skillLevel": 1, "skillIcon": "Skill_A_03"}, {"skillId": "10502", "skillName": "烈烧佑命之侍护", "skillLevel": 1, "skillIcon": "Skill_S_Tohma_01"}, {"skillId": "10505", "skillName": "真红炽火之大铠", "skillLevel": 1, "skillIcon": "Skill_E_Tohma_01"}], "avatarEnName": "Tohma", "talentList": [{"talentId": 501, "talentName": "同袍的义理", "talentIcon": "UI_Talent_S_Tohma_01"}, {"talentId": 502, "talentName": "僚佐的才巧", "talentIcon": "UI_Talent_S_Tohma_02"}, {"talentId": 503, "talentName": "御敌的执定", "talentIcon": "UI_Talent_U_Tohma_01"}], "avatarFightProp": {"hp": 10144.240234375, "baseHp": 2872.3681640625, "addHp": 7271.8720703125, "atk": 1059.1856689453125, "baseAtk": 510.46307373046875, "addAtk": 548.7225952148438, "def": 266.60711669921875, "baseDef": 208.73712158203125, "addDef": 57.8699951171875, "elementalMastery": 37.29999923706055, "critRate": 0.7208200097084045, "critDmg": 2.031100034713745, "energyRecharge": 1.1814000606536865, "healBonus": 0, "healedBonus": 0, "physicalDmgSub": 0, "physicalDmgBonus": 0, "dmgBonus": 0.4659999907016754}, "weaponInfo": {"itemId": 13405, "nameTextMapHash": "4049410651", "weaponIcon": "UI_EquipIcon_Pole_Gladiator", "weaponType": "长柄武器", "weaponName": "决斗之枪", "weaponStar": 4, "promoteLevel": 6, "weaponLevel": 90, "weaponAffix": 1, "weaponStats": [{"appendPropId": "FIGHT_PROP_BASE_ATTACK", "statName": "基础攻击力", "statValue": 454}, {"appendPropId": "FIGHT_PROP_CRITICAL", "statName": "暴击率", "statValue": 36.8}], "weaponEffect": "身边至少有2个敌人时，获得16%攻击力提升与16%防御力提升；身边的敌人少于2个时，获得24%攻击力提升。"}, "equipSets": {"type": "22", "set": "昔日宗室之仪追忆之注连"}, "equipList": [{"itemId": 94544, "nameTextMapHash": "600966780", "icon": "UI_RelicIcon_15020_4", "aritifactName": "明威之镡", "aritifactSetsName": "绝缘之旗印", "aritifactSetPiece": "flower", "aritifactPieceName": "生之花", "aritifactStar": 5, "aritifactLevel": 20, "reliquaryMainstat": {"mainPropId": "FIGHT_PROP_HP", "statValue": 4780, "statName": "血量"}, "reliquarySubstats": [{"appendPropId": "FIGHT_PROP_CRITICAL_HURT", "statValue": 28, "statName": "暴击伤害"}, {"appendPropId": "FIGHT_PROP_CRITICAL", "statValue": 6.2, "statName": "暴击率"}, {"appendPropId": "FIGHT_PROP_HP_PERCENT", "statValue": 5.8, "statName": "百分比血量"}, {"appendPropId": "FIGHT_PROP_DEFENSE", "statValue": 42, "statName": "防御力"}]}, {"itemId": 81523, "nameTextMapHash": "815154916", "icon": "UI_RelicIcon_15007_2", "aritifactName": "宗室之翎", "aritifactSetsName": "昔日宗室之仪", "aritifactSetPiece": "plume", "aritifactPieceName": "死之羽", "aritifactStar": 5, "aritifactLevel": 20, "reliquaryMainstat": {"mainPropId": "FIGHT_PROP_ATTACK", "statValue": 311, "statName": "攻击力"}, "reliquarySubstats": [{"appendPropId": "FIGHT_PROP_CRITICAL", "statValue": 6.6, "statName": "暴击率"}, {"appendPropId": "FIGHT_PROP_CRITICAL_HURT", "statValue": 21, "statName": "暴击伤害"}, {"appendPropId": "FIGHT_PROP_ATTACK_PERCENT", "statValue": 4.7, "statName": "百分比攻击力"}, {"appendPropId": "FIGHT_PROP_ELEMENT_MASTERY", "statValue": 37, "statName": "元素精通"}]}, {"itemId": 93553, "nameTextMapHash": "2767946268", "icon": "UI_RelicIcon_15019_5", "aritifactName": "朝露之时", "aritifactSetsName": "追忆之注连", "aritifactSetPiece": "sands", "aritifactPieceName": "时之沙", "aritifactStar": 5, "aritifactLevel": 20, "reliquaryMainstat": {"mainPropId": "FIGHT_PROP_HP_PERCENT", "statValue": 46.6, "statName": "百分比血量"}, "reliquarySubstats": [{"appendPropId": "FIGHT_PROP_CRITICAL_HURT", "statValue": 21, "statName": "暴击伤害"}, {"appendPropId": "FIGHT_PROP_CHARGE_EFFICIENCY", "statValue": 11.7, "statName": "元素充能效率"}, {"appendPropId": "FIGHT_PROP_HP", "statValue": 269, "statName": "血量"}, {"appendPropId": "FIGHT_PROP_ATTACK_PERCENT", "statValue": 9.3, "statName": "百分比攻击力"}]}, {"itemId": 93513, "nameTextMapHash": "2718771884", "icon": "UI_RelicIcon_15019_1", "aritifactName": "祈望之心", "aritifactSetsName": "追忆之注连", "aritifactSetPiece": "goblet", "aritifactPieceName": "空之杯", "aritifactStar": 5, "aritifactLevel": 20, "reliquaryMainstat": {"mainPropId": "FIGHT_PROP_ROCK_ADD_HURT", "statValue": 46.6, "statName": "岩元素伤害加成"}, "reliquarySubstats": [{"appendPropId": "FIGHT_PROP_CRITICAL", "statValue": 7.4, "statName": "暴击率"}, {"appendPropId": "FIGHT_PROP_HP", "statValue": 418, "statName": "血量"}, {"appendPropId": "FIGHT_PROP_CRITICAL_HURT", "statValue": 21, "statName": "暴击伤害"}, {"appendPropId": "FIGHT_PROP_DEFENSE", "statValue": 16, "statName": "防御力"}]}, {"itemId": 81533, "nameTextMapHash": "73409068", "icon": "UI_RelicIcon_15007_3", "aritifactName": "宗室面具", "aritifactSetsName": "昔日宗室之仪", "aritifactSetPiece": "circlet", "aritifactPieceName": "理之冠", "aritifactStar": 5, "aritifactLevel": 20, "reliquaryMainstat": {"mainPropId": "FIGHT_PROP_CRITICAL_HURT", "statValue": 62.2, "statName": "暴击伤害"}, "reliquarySubstats": [{"appendPropId": "FIGHT_PROP_CHARGE_EFFICIENCY", "statValue": 6.5, "statName": "元素充能效率"}, {"appendPropId": "FIGHT_PROP_ATTACK_PERCENT", "statValue": 14.6, "statName": "百分比攻击力"}, {"appendPropId": "FIGHT_PROP_CRITICAL", "statValue": 10.1, "statName": "暴击率"}, {"appendPropId": "FIGHT_PROP_HP", "statValue": 299, "statName": "血量"}]}]}