{"playerUid": "181761689", "playerName": "阿晴", "avatarId": 10000016, "avatarName": "迪卢克", "avatarFetter": 10, "avatarLevel": "90", "avatarElement": "Pyro", "dataTime": "2022-08-10 02:38:35", "avatarSkill": [{"skillId": "10160", "skillName": "普通攻击·淬炼之剑", "skillLevel": 9, "skillIcon": "Skill_A_04"}, {"skillId": "10161", "skillName": "逆焰之刃", "skillLevel": 9, "skillIcon": "Skill_S_Diluc_01_01"}, {"skillId": "10165", "skillName": "黎明", "skillLevel": 9, "skillIcon": "Skill_E_Diluc_01"}], "avatarEnName": "Diluc", "talentList": [{"talentId": 161, "talentName": "罪罚裁断", "talentIcon": "UI_Talent_S_Diluc_01"}], "avatarFightProp": {"hp": 18985.556640625, "baseHp": 12980.666015625, "addHp": 6004.890625, "atk": 1237.983154296875, "baseAtk": 844.4556884765625, "addAtk": 393.5274658203125, "def": 802.4454956054688, "baseDef": 783.9254760742188, "addDef": 18.52001953125, "elementalMastery": 0, "critRate": 0.413100004196167, "critDmg": 1.6805799007415771, "energyRecharge": 1.1101000308990479, "healBonus": 0, "healedBonus": 0, "physicalDmgSub": 0, "physicalDmgBonus": 0, "dmgBonus": 0.6159999966621399}, "weaponInfo": {"itemId": 12408, "nameTextMapHash": "20848859", "weaponIcon": "UI_EquipIcon_Claymore_Blackrock", "weaponType": "双手剑", "weaponName": "黑岩斩刀", "weaponStar": 4, "promoteLevel": 6, "weaponLevel": 90, "weaponAffix": 1, "weaponStats": [{"appendPropId": "FIGHT_PROP_BASE_ATTACK", "statName": "基础攻击力", "statValue": 510}, {"appendPropId": "FIGHT_PROP_CRITICAL_HURT", "statName": "暴击伤害", "statValue": 55.1}], "weaponEffect": "击败敌人后，攻击力提升12%，持续30秒。该效果至多叠加3层，每层持续时间独立。"}, "equipSets": {"type": "2", "set": "炽烈的炎之魔女"}, "equipList": [{"itemId": 80543, "nameTextMapHash": "1149648428", "icon": "UI_RelicIcon_15006_4", "aritifactName": "魔女的炎之花", "aritifactSetsName": "炽烈的炎之魔女", "aritifactSetPiece": "flower", "aritifactPieceName": "生之花", "aritifactStar": 5, "aritifactLevel": 20, "reliquaryMainstat": {"mainPropId": "FIGHT_PROP_HP", "statValue": 4780, "statName": "血量"}, "reliquarySubstats": [{"appendPropId": "FIGHT_PROP_CHARGE_EFFICIENCY", "statValue": 11, "statName": "元素充能效率"}, {"appendPropId": "FIGHT_PROP_CRITICAL_HURT", "statValue": 28.7, "statName": "暴击伤害"}, {"appendPropId": "FIGHT_PROP_ATTACK", "statValue": 14, "statName": "攻击力"}, {"appendPropId": "FIGHT_PROP_CRITICAL", "statValue": 3.1, "statName": "暴击率"}]}, {"itemId": 80523, "nameTextMapHash": "3216935684", "icon": "UI_RelicIcon_15006_2", "aritifactName": "魔女常燃之羽", "aritifactSetsName": "炽烈的炎之魔女", "aritifactSetPiece": "plume", "aritifactPieceName": "死之羽", "aritifactStar": 5, "aritifactLevel": 20, "reliquaryMainstat": {"mainPropId": "FIGHT_PROP_ATTACK", "statValue": 311, "statName": "攻击力"}, "reliquarySubstats": [{"appendPropId": "FIGHT_PROP_CRITICAL", "statValue": 10.1, "statName": "暴击率"}, {"appendPropId": "FIGHT_PROP_DEFENSE", "statValue": 19, "statName": "防御力"}, {"appendPropId": "FIGHT_PROP_CRITICAL_HURT", "statValue": 13.2, "statName": "暴击伤害"}, {"appendPropId": "FIGHT_PROP_HP", "statValue": 538, "statName": "血量"}]}, {"itemId": 81514, "nameTextMapHash": "688784652", "icon": "UI_RelicIcon_15007_1", "aritifactName": "宗室银瓮", "aritifactSetsName": "昔日宗室之仪", "aritifactSetPiece": "goblet", "aritifactPieceName": "空之杯", "aritifactStar": 5, "aritifactLevel": 20, "reliquaryMainstat": {"mainPropId": "FIGHT_PROP_FIRE_ADD_HURT", "statValue": 46.6, "statName": "火元素伤害加成"}, "reliquarySubstats": [{"appendPropId": "FIGHT_PROP_CRITICAL_HURT", "statValue": 21, "statName": "暴击伤害"}, {"appendPropId": "FIGHT_PROP_ATTACK_PERCENT", "statValue": 8.2, "statName": "百分比攻击力"}, {"appendPropId": "FIGHT_PROP_HP", "statValue": 687, "statName": "血量"}, {"appendPropId": "FIGHT_PROP_CRITICAL", "statValue": 3.9, "statName": "暴击率"}]}]}